pydoctor/__init__.py
pydoctor/__main__.py
pydoctor/_configparser.py
pydoctor/astbuilder.py
pydoctor/astutils.py
pydoctor/driver.py
pydoctor/epydoc2stan.py
pydoctor/factory.py
pydoctor/linker.py
pydoctor/model.py
pydoctor/mro.py
pydoctor/node2stan.py
pydoctor/options.py
pydoctor/qnmatch.py
pydoctor/sphinx.py
pydoctor/stanutils.py
pydoctor/tokenutils.py
pydoctor/utils.py
pydoctor/visitor.py
pydoctor/__pycache__/__init__.cpython-312.opt-1.pyc
pydoctor/__pycache__/__main__.cpython-312.opt-1.pyc
pydoctor/__pycache__/_configparser.cpython-312.opt-1.pyc
pydoctor/__pycache__/astbuilder.cpython-312.opt-1.pyc
pydoctor/__pycache__/astutils.cpython-312.opt-1.pyc
pydoctor/__pycache__/driver.cpython-312.opt-1.pyc
pydoctor/__pycache__/epydoc2stan.cpython-312.opt-1.pyc
pydoctor/__pycache__/factory.cpython-312.opt-1.pyc
pydoctor/__pycache__/linker.cpython-312.opt-1.pyc
pydoctor/__pycache__/model.cpython-312.opt-1.pyc
pydoctor/__pycache__/mro.cpython-312.opt-1.pyc
pydoctor/__pycache__/node2stan.cpython-312.opt-1.pyc
pydoctor/__pycache__/options.cpython-312.opt-1.pyc
pydoctor/__pycache__/qnmatch.cpython-312.opt-1.pyc
pydoctor/__pycache__/sphinx.cpython-312.opt-1.pyc
pydoctor/__pycache__/stanutils.cpython-312.opt-1.pyc
pydoctor/__pycache__/tokenutils.cpython-312.opt-1.pyc
pydoctor/__pycache__/utils.cpython-312.opt-1.pyc
pydoctor/__pycache__/visitor.cpython-312.opt-1.pyc
pydoctor/epydoc/__init__.py
pydoctor/epydoc/doctest.py
pydoctor/epydoc/docutils.py
pydoctor/epydoc/sre_constants36.py
pydoctor/epydoc/sre_parse36.py
pydoctor/epydoc/__pycache__/__init__.cpython-312.opt-1.pyc
pydoctor/epydoc/__pycache__/doctest.cpython-312.opt-1.pyc
pydoctor/epydoc/__pycache__/docutils.cpython-312.opt-1.pyc
pydoctor/epydoc/__pycache__/sre_constants36.cpython-312.opt-1.pyc
pydoctor/epydoc/__pycache__/sre_parse36.cpython-312.opt-1.pyc
pydoctor/epydoc/markup/__init__.py
pydoctor/epydoc/markup/_napoleon.py
pydoctor/epydoc/markup/_pyval_repr.py
pydoctor/epydoc/markup/_types.py
pydoctor-25.10.1.dist-info/licenses/LICENSE.txt
pydoctor-25.10.1.dist-info/METADATA
pydoctor-25.10.1.dist-info/WHEEL
pydoctor-25.10.1.dist-info/entry_points.txt
pydoctor-25.10.1.dist-info/top_level.txt
pydoctor-25.10.1.dist-info/RECORD
