Metadata-Version: 2.4
Name: pydoctor
Version: 25.10.1
Summary: API doc generator.
Home-page: https://github.com/twisted/pydoctor
Author: Michael Hudson-Doyle
Author-email: micahel@gmail.com
Maintainer: Maarten ter Huurne
Maintainer-email: maarten@boxingbeetle.com
License: MIT/X11
Project-URL: Issue Tracker, https://github.com/twisted/pydoctor/issues
Project-URL: Repository, https://github.com/twisted/pydoctor
Project-URL: Documentation, https://pydoctor.readthedocs.io/
Classifier: Development Status :: 6 - Mature
Classifier: Intended Audience :: Developers
Classifier: License :: OSI Approved :: MIT License
Classifier: Operating System :: OS Independent
Classifier: Programming Language :: Python :: 3
Classifier: Programming Language :: Python :: 3.9
Classifier: Programming Language :: Python :: 3.10
Classifier: Programming Language :: Python :: 3.11
Classifier: Programming Language :: Python :: 3.12
Classifier: Programming Language :: Python :: 3.13
Classifier: Programming Language :: Python :: 3.14
Classifier: Programming Language :: Python :: Implementation :: CPython
Classifier: Programming Language :: Python :: Implementation :: PyPy
Classifier: Topic :: Documentation
Classifier: Topic :: Software Development :: Documentation
Requires-Python: >=3.9
License-File: LICENSE.txt
Requires-Dist: platformdirs
Requires-Dist: CacheControl[filecache]>=0.12.14
Requires-Dist: Twisted
Requires-Dist: urllib3
Requires-Dist: requests
Requires-Dist: attrs
Requires-Dist: docutils>=0.17
Requires-Dist: lunr<0.9.0,>=0.6.2
Requires-Dist: configargparse
Requires-Dist: tomli; python_version < "3.11"
Provides-Extra: docs
Requires-Dist: Sphinx; extra == "docs"
Requires-Dist: sphinx_rtd_theme; extra == "docs"
Requires-Dist: sphinxcontrib-spelling; extra == "docs"
Requires-Dist: sphinx-argparse; extra == "docs"
Provides-Extra: rst
Requires-Dist: docutils; extra == "rst"
Provides-Extra: test
Requires-Dist: docutils>=0.18.1; extra == "test"
Requires-Dist: coverage; extra == "test"
Requires-Dist: pytest; extra == "test"
Requires-Dist: pytest-xdist; extra == "test"
Requires-Dist: hypothesis; extra == "test"
Requires-Dist: cython-test-exception-raiser; extra == "test"
Requires-Dist: bs4; extra == "test"
Requires-Dist: Sphinx; extra == "test"
Requires-Dist: pytest-subtests; extra == "test"
Requires-Dist: setuptools; extra == "test"
Provides-Extra: mypy
Requires-Dist: mypy>=1.16.1; extra == "mypy"
Requires-Dist: mypy-zope; extra == "mypy"
Requires-Dist: typing-extensions; extra == "mypy"
Requires-Dist: hypothesis; extra == "mypy"
Requires-Dist: pytest>=6.0.0; extra == "mypy"
Requires-Dist: sphinx>=3.4.0; extra == "mypy"
Requires-Dist: twisted; extra == "mypy"
Requires-Dist: types-requests; extra == "mypy"
Requires-Dist: types-docutils; extra == "mypy"
Dynamic: description
Dynamic: license-file
